topsis/__init__.py
topsis/topsis.py
topsis_jamesfallon-0.2.3.dist-info/LICENSE
topsis_jamesfallon-0.2.3.dist-info/METADATA
topsis_jamesfallon-0.2.3.dist-info/WHEEL
topsis_jamesfallon-0.2.3.dist-info/top_level.txt
topsis_jamesfallon-0.2.3.dist-info/RECORD
