Metadata-Version: 2.1
Name: topsis-jamesfallon
Version: 0.2.3
Summary: Implementation of TOPSIS decision making
Home-page: https://gitlab.com/jamesfallon/topsis-python
Author: James Fallon
Author-email: j.fallon@pgr.reading.ac.uk
License: MIT
Platform: UNKNOWN
Classifier: Programming Language :: Python :: 3
Classifier: License :: OSI Approved :: MIT License
Classifier: Operating System :: OS Independent
Requires-Dist: numpy
